MANIFEST.in
README.rst
setup.py
docs/HISTORY.txt
docs/LICENSE.GPL
docs/LICENSE.txt
ftw/__init__.py
ftw.recipe.translations.egg-info/PKG-INFO
ftw.recipe.translations.egg-info/SOURCES.txt
ftw.recipe.translations.egg-info/dependency_links.txt
ftw.recipe.translations.egg-info/entry_points.txt
ftw.recipe.translations.egg-info/namespace_packages.txt
ftw.recipe.translations.egg-info/not-zip-safe
ftw.recipe.translations.egg-info/requires.txt
ftw.recipe.translations.egg-info/top_level.txt
ftw/recipe/__init__.py
ftw/recipe/translations/__init__.py
ftw/recipe/translations/catalog.py
ftw/recipe/translations/discovery.py
ftw/recipe/translations/google.py
ftw/recipe/translations/i18ntools.py
ftw/recipe/translations/inflator.py
ftw/recipe/translations/loader.py
ftw/recipe/translations/progresslogger.py
ftw/recipe/translations/testing.py
ftw/recipe/translations/utils.py
ftw/recipe/translations/writer.py
ftw/recipe/translations/i18nbuild/__init__.py
ftw/recipe/translations/i18nbuild/command.py
ftw/recipe/translations/i18nbuild/recipe.py
ftw/recipe/translations/masstranslate/__init__.py
ftw/recipe/translations/masstranslate/command.py
ftw/recipe/translations/masstranslate/download.py
ftw/recipe/translations/masstranslate/recipe.py
ftw/recipe/translations/masstranslate/sync.py
ftw/recipe/translations/masstranslate/upload.py
ftw/recipe/translations/tests/__init__.py
ftw/recipe/translations/tests/fshelpers.py
ftw/recipe/translations/tests/pohelpers.py
ftw/recipe/translations/tests/test_discovery.py
ftw/recipe/translations/tests/test_i18nbuild_command.py
ftw/recipe/translations/tests/test_i18nbuild_integration.py
ftw/recipe/translations/tests/test_i18nbuild_recipe.py
ftw/recipe/translations/tests/test_i18ntools.py
ftw/recipe/translations/tests/test_inflator.py
ftw/recipe/translations/tests/test_loader.py
ftw/recipe/translations/tests/test_masstranslate_download.py
ftw/recipe/translations/tests/test_masstranslate_recipe.py
ftw/recipe/translations/tests/test_masstranslate_sync.py
ftw/recipe/translations/tests/test_masstranslate_upload.py
ftw/recipe/translations/tests/test_utils.py
ftw/recipe/translations/tests/test_writer.py
ftw/recipe/translations/tests/assets/empty.po
ftw/recipe/translations/tests/assets/empty.pot
ftw/recipe/translations/tests/assets/foo-de.po
ftw/recipe/translations/tests/assets/foo.pot
ftw/recipe/translations/tests/assets/translated_content.json
