Metadata-Version: 1.0
Name: ftw.recipe.translations
Version: 1.2.2
Summary: Mass export / import of translations into Google Docs Spreadsheets
Home-page: https://github.com/4teamwork/ftw.recipe.translations
Author: 4teamwork AG
Author-email: mailto:info@4teamwork.ch
License: GPL2
Keywords: ftw recipe translations import export google docs
Platform: UNKNOWN
Classifier: Framework :: Plone
Classifier: Intended Audience :: Developers
Classifier: Topic :: Software Development :: Libraries :: Python Modules
